prethink/__init__.py
prethink/errors.py
prethink/vendor/bin/rethinkdb-dump
prethink/vendor/bin/rethinkdb-export
prethink/vendor/bin/rethinkdb-import
prethink/vendor/bin/rethinkdb-index-rebuild
prethink/vendor/bin/rethinkdb-repl
prethink/vendor/bin/rethinkdb-restore
prethink/vendor/rethinkdb/__init__.py
prethink/vendor/rethinkdb/__main__.py
prethink/vendor/rethinkdb/_dump.py
prethink/vendor/rethinkdb/_export.py
prethink/vendor/rethinkdb/_import.py
prethink/vendor/rethinkdb/_index_rebuild.py
prethink/vendor/rethinkdb/_restore.py
prethink/vendor/rethinkdb/ast.py
prethink/vendor/rethinkdb/asyncio_net/__init__.py
prethink/vendor/rethinkdb/asyncio_net/net_asyncio.py
prethink/vendor/rethinkdb/backports/__init__.py
prethink/vendor/rethinkdb/backports/ssl_match_hostname/LICENSE.txt
prethink/vendor/rethinkdb/backports/ssl_match_hostname/README.txt
prethink/vendor/rethinkdb/backports/ssl_match_hostname/__init__.py
prethink/vendor/rethinkdb/docs.py
prethink/vendor/rethinkdb/errors.py
prethink/vendor/rethinkdb/gevent_net/__init__.py
prethink/vendor/rethinkdb/gevent_net/net_gevent.py
prethink/vendor/rethinkdb/handshake.py
prethink/vendor/rethinkdb/helpers.py
prethink/vendor/rethinkdb/logger.py
prethink/vendor/rethinkdb/net.py
prethink/vendor/rethinkdb/ql2_pb2.py
prethink/vendor/rethinkdb/query.py
prethink/vendor/rethinkdb/tornado_net/__init__.py
prethink/vendor/rethinkdb/tornado_net/net_tornado.py
prethink/vendor/rethinkdb/trio_net/__init__.py
prethink/vendor/rethinkdb/trio_net/net_trio.py
prethink/vendor/rethinkdb/twisted_net/__init__.py
prethink/vendor/rethinkdb/twisted_net/net_twisted.py
prethink/vendor/rethinkdb/utils_common.py
prethink/vendor/rethinkdb/version.py
prethink/vendor/rethinkdb-2.4.7.dist-info/INSTALLER
prethink/vendor/rethinkdb-2.4.7.dist-info/LICENSE
prethink/vendor/rethinkdb-2.4.7.dist-info/METADATA
prethink/vendor/rethinkdb-2.4.7.dist-info/RECORD
prethink/vendor/rethinkdb-2.4.7.dist-info/WHEEL
prethink/vendor/rethinkdb-2.4.7.dist-info/entry_points.txt
prethink/vendor/rethinkdb-2.4.7.dist-info/top_level.txt
prethink/vendor/rethinkdb-2.4.7.dist-info/zip-safe
prethink/vendor/six-1.15.0.dist-info/INSTALLER
prethink/vendor/six-1.15.0.dist-info/LICENSE
prethink/vendor/six-1.15.0.dist-info/METADATA
prethink/vendor/six-1.15.0.dist-info/RECORD
prethink/vendor/six-1.15.0.dist-info/WHEEL
prethink/vendor/six-1.15.0.dist-info/top_level.txt
prethink/vendor/six.py
prethink-0.2.0.dist-info/LICENSE
prethink-0.2.0.dist-info/WHEEL
prethink-0.2.0.dist-info/METADATA
prethink-0.2.0.dist-info/RECORD
