Metadata-Version: 2.1
Name: prethink
Version: 0.2.0
Summary: 
Author: Logi Leifsson
Author-email: logileifs@gmail.com
Requires-Python: >=3.7,<4.0
Classifier: Programming Language :: Python :: 3
Classifier: Programming Language :: Python :: 3.7
Classifier: Programming Language :: Python :: 3.8
Classifier: Programming Language :: Python :: 3.9
Requires-Dist: inflection (>=0.5.1,<0.6.0)
Requires-Dist: setuptools (>=50.3.2,<51.0.0)
